{
  "Name": "refundSaga",
  "Comment": "Refund saga for after-sale process",
  "Version": "1.0.0",
  "StartState": "refundApply",
  "States": {
    "refundApply": {
      "type": "serviceTask",
      "serviceName": "orderRefundSagaService.applyRefund",
      "compensateState": "refundApplyCompensate",
      "next": "refundCreate"
    },
    "refundCreate": {
      "type": "serviceTask",
      "serviceName": "orderRefundSagaService.createRefund",
      "compensateState": "refundCreateCompensate",
      "end": true
    },
    "refundApplyCompensate": {
      "type": "serviceTask",
      "serviceName": "orderRefundSagaService.cancelRefund",
      "end": true
    },
    "refundCreateCompensate": {
      "type": "serviceTask",
      "serviceName": "orderRefundSagaService.cancelRefundWithPayment",
      "end": true
    }
  }
}
